search_hound_ai/__init__.py
search_hound_ai/app.py
search_hound_ai/hound_client_commands.py
search_hound_ai/openai_lib.py
search_hound_ai/search_hound_lib.py
search_hound_ai-0.1.12.dist-info/LICENSE
search_hound_ai-0.1.12.dist-info/METADATA
search_hound_ai-0.1.12.dist-info/WHEEL
search_hound_ai-0.1.12.dist-info/entry_points.txt
search_hound_ai-0.1.12.dist-info/RECORD
