Metadata-Version: 2.1
Name: search-hound-ai
Version: 0.1.12
Summary: A CLI for GPT with a focus on simplicity and ease of use. For developer just wanting to use gpt in there command line.
Author: Martin Patino
Author-email: martin@sibipro.com
Requires-Python: >=3.11,<4.0
Classifier: Programming Language :: Python :: 3
Classifier: Programming Language :: Python :: 3.11
Requires-Dist: langchain (>=0.0.146,<0.0.147)
Requires-Dist: load-dotenv (>=0.1.0,<0.2.0)
Requires-Dist: logging (>=0.4.9.6,<0.5.0.0)
Requires-Dist: openai (>=0.27.4,<0.28.0)
Requires-Dist: typer[all] (>=0.7.0,<0.8.0)
